et_rstor/__init__.py
et_rstor-1.2.0.dist-info/entry_points.txt
et_rstor-1.2.0.dist-info/LICENSE
et_rstor-1.2.0.dist-info/WHEEL
et_rstor-1.2.0.dist-info/METADATA
et_rstor-1.2.0.dist-info/RECORD
