Metadata-Version: 2.1
Name: et-rstor
Version: 1.2.0
Summary: <Enter a one-sentence description of this project here.>
Home-page: https://github.com/etijskens/et-rstor
License: MIT
Keywords: packaging,poetry
Author: Bert Tijskens
Author-email: engelbert.tijskens@uantwerpen.be
Requires-Python: >=3.7,<4.0
Classifier: License :: OSI Approved :: MIT License
Classifier: Programming Language :: Python :: 3
Classifier: Programming Language :: Python :: 3.7
Classifier: Programming Language :: Python :: 3.8
Classifier: Programming Language :: Python :: 3.9
Project-URL: Repository, https://github.com/etijskens/et-rstor
